{
    "grenade": {
        "level_1": 1000,
        "level_2": 1300,
        "level_3": 1600,
        "level_4": 2000,
        "level_5": 2500,
        "level_6": 3000,
        "level_7": 3600,
        "level_8": 4200,
        "level_9": 4900,
        "level_10": 5700
    },
    "toxic_grenade": {
        "level_1": 1000,
        "level_2": 1300,
        "level_3": 1600,
        "level_4": 2000,
        "level_5": 2500,
        "level_6": 3000,
        "level_7": 3600,
        "level_8": 4200,
        "level_9": 4900,
        "level_10": 5700
    },
    "drone": {
        "level_1": 1000,
        "level_2": 1300,
        "level_3": 1600,
        "level_4": 2000,
        "level_5": 2500,
        "level_6": 3000,
        "level_7": 3600,
        "level_8": 4200,
        "level_9": 4900,
        "level_10": 5700
    },
    "missile": {
        "level_1": 1200,
        "level_2": 1500,
        "level_3": 1800,
        "level_4": 2200,
        "level_5": 2700,
        "level_6": 3300,
        "level_7": 4000,
        "level_8": 4700,
        "level_9": 5500,
        "level_10": 6400
    },
    "laser_probe": {
        "level_1": 1200,
        "level_2": 1500,
        "level_3": 1800,
        "level_4": 2200,
        "level_5": 2700,
        "level_6": 3300,
        "level_7": 4000,
        "level_8": 4700,
        "level_9": 5500,
        "level_10": 6400
    }
}